procman/__init__.py
procman/__main__.py
procman/cli.py
procman/detachable_tabs.py
procman/helpers.py
procman/procman.py
procman-2.3.1.dist-info/METADATA
procman-2.3.1.dist-info/WHEEL
procman-2.3.1.dist-info/licenses/LICENSE
procman-2.3.1.dist-info/RECORD
