Metadata-Version: 2.4
Name: procman
Version: 2.3.1
Summary: Tabbed GUI to start/stop/monitor programs
Project-URL: Homepage, https://github.com/ASukhanov/procman
Author-email: Andrey Sukhanov <cyxandr@gmail.com>
License-File: LICENSE
Classifier: License :: OSI Approved :: MIT License
Classifier: Operating System :: OS Independent
Classifier: Programming Language :: Python :: 3
Requires-Python: >=3.9
Requires-Dist: pyqt5
